tests/__init__.py
tests/models_test.py
tests/doubles.py
tests/api_test.py
smsapi_contacts-1.0.5.dist-info/DESCRIPTION.rst
smsapi_contacts-1.0.5.dist-info/RECORD
smsapi_contacts-1.0.5.dist-info/METADATA
smsapi_contacts-1.0.5.dist-info/metadata.json
smsapi_contacts-1.0.5.dist-info/top_level.txt
smsapi_contacts-1.0.5.dist-info/WHEEL
smsapicontacts/exception.py
smsapicontacts/__init__.py
smsapicontacts/api.py
smsapicontacts/models.py
smsapicontacts/endpoint.py
smsapicontacts/utils.py
smsapicontacts/compat.py
