Metadata-Version: 2.0
Name: smsapi-contacts
Version: 1.0.5
Summary: Python client for SMSAPI contacts rest API.
Home-page: https://github.com/smsapi/smsapi-contacts-python-client
Author: SMSAPI
Author-email: bok@smsapi.pl
License: Copyright 2015 SMSAPI
Requires-Dist: requests
